kraken_scraper/datapoint.py
kraken_scraper/kraken_scraper.py
kraken_scraper/scraper_files.py
kraken_scraper/scraper_main.py
kraken_scraper/scraper_schemas.py
kraken_scraper/scraper_tables.py
kraken_scraper/scraper_videos.py
kraken_scrape-0.0.1.dist-info/LICENSE.txt
kraken_scrape-0.0.1.dist-info/METADATA
kraken_scrape-0.0.1.dist-info/WHEEL
kraken_scrape-0.0.1.dist-info/top_level.txt
kraken_scrape-0.0.1.dist-info/RECORD
